{
  "heatingMode": "manual",
  "heatingController": { "isConnected": true, "isOn": false },
  "heatingSensors": {
    "livingRoom": { "isConnected": true, "temperature": 14.2, "humidity": 10, "pressure": 101459.2 },
    "kitchen": { "isConnected": true, "temperature": 16, "humidity": 10, "pressure": 101459.2 },
    "liamsRoom": { "isConnected": true, "temperature": 15.1, "humidity": 10, "pressure": 101459.2 },
    "study": { "isConnected": true, "temperature": 8.9, "humidity": 10, "pressure": 101459.2 },
    "ourRoom": { "isConnected": true, "temperature": 18.2, "humidity": 10, "pressure": 101459.2 }
  },
  "radiatorValves": {
    "livingRoom": { "isConnected": true, "isOpen": true, "demand": false },
    "kitchen": { "isConnected": true, "isOpen": true, "demand": false },
    "liamsRoom": { "isConnected": true, "isOpen": true, "demand": false },
    "study": { "isConnected": true, "isOpen": true, "demand": false },
    "ourRoom": { "isConnected": true, "isOpen": true, "demand": false }
  },
  "setpoints": {
    "livingRoom": [15, 15, 15, 15, 15, 15, 15, 15, 15, 15, 15, 15, 15, 15, 15, 15, 15, 18, 18, 18, 18, 15, 16, 18],
    "kitchen": [15, 15, 15, 15, 15, 15, 15, 15, 15, 15, 15, 15, 12, 13, 14, 15, 17, 17, 18, 18, 18, 18, 16, 17],
    "study": [16, 16, 16, 16, 16, 16, 16, 16, 16, 16, 16, 16, 16, 16, 16, 16, 16, 16, 16, 16, 16, 16, 16, 16],
    "liamsRoom": [6, 6, 6, 6, 6, 6, 6, 6, 17, 18, 18, 18, 18, 18, 18, 18, 18, 18, 19, 19, 19, 19, 17, 17],
    "ourRoom": [15, 15, 15, 15, 15, 15, 15, 15, 19, 19, 19, 19, 18, 18, 18, 18, 18, 18, 18, 18, 18, 18, 20, 16]
  },
  "heatingSchedule": {
    "monday": [8, 10, 16.3, 18.3],
    "tuesday": [8, 10, 16.3, 18.3],
    "wednesday": [8, 10, 16.3, 17.15],
    "thursday": [8, 10, 16.3, 18.3],
    "friday": [8, 10, 16.3, 18.3],
    "saturday": [10, 12, 17, 19.3],
    "sunday": [10, 12, 17, 20],
    "boostTime": 1611771652455,
    "radiatorFanTime": 1611772851231,
    "heatingTime": 1611771951231
  },
  "heatingZones": {
    "isAuto": true,
    "livingRoom": { "demand": true },
    "kitchen": { "demand": true },
    "liamsRoom": { "demand": true },
    "study": { "demand": true },
    "ourRoom": { "demand": true },
    "radiatorFanTime": 1611700319349,
    "heatingTime": 1611699419349
  },
  "heatingManual": { "radiatorFanTime": 1611503585005, "heatingTime": 1611502685005 },
  "houseStats": { "average": 14.5, "minimumTemp": 8.9, "maximumTemp": 18.2 },
  "outside": {
    "current": { "temperature": 2.67, "humidity": 1, "pressure": 1009.4, "windSpeed": 2.9, "windBearing": 219, "cloudCover": 1, "isConnected": true },
    "next24Hrs": [
      2.7,
      2.73,
      2.7,
      2.93,
      2.91,
      2.86,
      2.87,
      2.77,
      2.56,
      2.54,
      2.69,
      2.91,
      3.14,
      3.4,
      3.63,
      3.95,
      4.65,
      5.93,
      10.04,
      10.65,
      10.7,
      10.66,
      6.86,
      5.6
    ]
  }
}
